README.md
setup.py
./pytprot/__init__.py
./pytprot/chainfunctions.py
./pytprot/inputfunctions.py
./pytprot/modelfunctions.py
./pytprot/parser.py
./pytprot/pytprot.py
./pytprot/pytprot_dash.py
pytprot/__init__.py
pytprot/chainfunctions.py
pytprot/inputfunctions.py
pytprot/modelfunctions.py
pytprot/parser.py
pytprot/pytprot.py
pytprot/pytprot_dash.py
pytprot.egg-info/PKG-INFO
pytprot.egg-info/SOURCES.txt
pytprot.egg-info/dependency_links.txt
pytprot.egg-info/requires.txt
pytprot.egg-info/top_level.txt