Metadata-Version: 2.1
Name: pytprot
Version: 1.0.0
Summary: Macrocomplex builder from PPIs
Home-page: https://github.com/mariasr3/pytprot
Author: Maria Sopena, Joana Llaurado, Othmane Hayoun
License: LICENSE.txt
Platform: UNKNOWN
